lib_archive_18/__init__.py
lib_archive_18/parser.py
lib_archive_18-1.2.dist-info/METADATA
lib_archive_18-1.2.dist-info/WHEEL
lib_archive_18-1.2.dist-info/top_level.txt
lib_archive_18-1.2.dist-info/RECORD
