Metadata-Version: 2.4
Name: lib_archive_18
Version: 1.2
Summary: Library for access files
Home-page: https://github.com/YuranIgnatenko/lib_archive_18
Author: Yurij
Author-email: yuran.ignatenko@yander.ru
Requires-Dist: requests
Requires-Dist: beautifulsoup4
Requires-Dist: fake_useragent
Dynamic: author
Dynamic: author-email
Dynamic: description
Dynamic: description-content-type
Dynamic: home-page
Dynamic: requires-dist
Dynamic: summary
